greenlamp-0.1.3.dist-info/METADATA
greenlamp-0.1.3.dist-info/WHEEL
greenlamp/__init__.py
greenlamp/_core.abi3.so
greenlamp/_core.pyi
greenlamp/differential/__init__.py
greenlamp/differential/discrete.py
greenlamp/matrix/__init__.py
greenlamp/matrix/elementary.py
greenlamp/py.typed
greenlamp-0.1.3.dist-info/RECORD
