Metadata-Version: 2.4
Name: greenlamp
Version: 0.1.3
Requires-Dist: maturin>=1.9.3
Requires-Dist: torch>=2.8.0
Requires-Dist: twine>=6.2.0
Summary: Add your description here
Author-email: greenlampgh <greenlampgh@gmail.com>
Requires-Python: >=3.11
